LICENSE.py
HOLY_BIBLE_from_Gch-1.0.dist-info/LICENSE.py
HOLY_BIBLE_from_Gch-1.0.dist-info/METADATA
HOLY_BIBLE_from_Gch-1.0.dist-info/WHEEL
HOLY_BIBLE_from_Gch-1.0.dist-info/top_level.txt
HOLY_BIBLE_from_Gch-1.0.dist-info/RECORD
