Metadata-Version: 2.1
Name: HOLY-BIBLE-from-Gch
Version: 1.0
Summary: HOLY BIBLE
Author: C. Praiseline Christina
Keywords: HOLY BIBLE
Classifier: Programming Language :: Python :: 3
Classifier: License :: OSI Approved :: MIT License
Classifier: Operating System :: OS Independent
Requires-Python: >=3.3
License-File: LICENSE.py
Requires-Dist: python (==3.4)
Requires-Dist: tkinter
